keras_model_client/__init__.py
keras_model_client/lib/__init__.py
keras_model_client/lib/models.py
keras_model_client/lib/ops.py
keras_model_client/scripts/predict.py
keras_model_client-0.1.1.dist-info/entry_points.txt
keras_model_client-0.1.1.dist-info/LICENSE
keras_model_client-0.1.1.dist-info/WHEEL
keras_model_client-0.1.1.dist-info/METADATA
keras_model_client-0.1.1.dist-info/RECORD
