Metadata-Version: 2.1
Name: keras-model-client
Version: 0.1.1
Summary: Python client API for the Keras Model Server
Author: Kevin Barnard
Author-email: kbarnard@mbari.org
Requires-Python: >=3.8,<4.0
Classifier: Programming Language :: Python :: 3
Classifier: Programming Language :: Python :: 3.10
Classifier: Programming Language :: Python :: 3.8
Classifier: Programming Language :: Python :: 3.9
Requires-Dist: dataclasses-json (>=0.5.7,<0.6.0)
Requires-Dist: requests (>=2.27.1,<3.0.0)
